{"data": {"answer": {"id": "QW5zd2VyQDA6MjU5ODA3MDc0", "__typename": "Answer", "aid": 259807074, "viewerIsAuthor": false, "isVisible": true, "numSharers": 5, "shouldShowSharePrompt": false, "viewer": {"useReactQuoraShareModal": true, "id": "Vmlld2VyQDA6MA==", "__typename": "Viewer", "uid": null, "user": null, "bundleSubscription": null, "directSubscriptions": [], "canReviewAnswers": false}, "creationTime": 1610596303217227, "updatedTime": 0, "author": {"id": "VXNlckAwOjQ2NzE0MjA0", "__typename": "User", "uid": 46714204, "isAnon": false, "profileImageUrl": "https://qph.fs.quoracdn.net/main-thumb-46714204-200-tdbtbwzjkgejhdqkeofjddnctinufcpw.jpeg", "isVerified": false, "businessStatus": null, "profileUrl": "/profile/Lee-Th\u00e9", "useTranslatedName": false, "names": [{"__typename": "UserName", "id": "VXNlck5hbWU6NDY3MTQyMDQ6TEFUTg==", "reverseOrder": false, "givenName": "Lee", "familyName": "Th\u00e9", "scriptCode": "LATN"}], "adminNames": [], "bundleSubscriptionStatus": 3}, "authorCredential": {"id": "TGlmZUV4cGVyaWVuY2VDcmVkZW50aWFsQDA6MjIxNTYwODE=", "__typename": "LifeExperienceCredential", "credentialId": 22156081, "translatedString": "Just 50 years of keeping abreast of events through a strongly empirical lens.", "experience": {"id": "VG9waWNAMDoxNDA0", "__typename": "Topic", "tid": 1404, "name": "Politics"}, "description": "Just 50 years of keeping abreast of events through a strongly empirical lens.", "isDefault": false, "isBad": false, "isEnqueued": false}, "isTranslated": false, "permaUrl": "/Would-strengthening-voter-identification-laws-help-restore-faith-in-American-elections/answer/Lee-Th\u00e9", "isOwnTranslation": false, "debugInfo": "{}", "question": {"id": "UXVlc3Rpb25AMDo4NDUzMDAxNQ==", "__typename": "Question", "qid": 84530015, "isDeleted": false, "url": "/Would-strengthening-voter-identification-laws-help-restore-faith-in-American-elections", "answerCount": 34, "title": "{\"sections\": [{\"spans\": [{\"text\": \"Would strengthening voter identification laws help restore faith in American elections?\", \"modifiers\": {}}], \"indent\": 0, \"quoted\": false, \"type\": \"plain\", \"is_rtl\": false}]}", "isPartnerQuestion": false, "asker": {"id": "VXNlckAwOjEwNzM1ODQ4", "__typename": "User", "isEmployee": false}, "debugInfo": "{}", "tribeItem": null, "viewer": {"id": "Vmlld2VyQDA6MA==", "__typename": "Viewer", "uid": null}, "network": {"nid": 0, "id": "TmV0d29yazow"}, "sourceUrl": null, "hadDetails": false, "viewerDisplayCredential": null}, "credibilityFacts": [{"id": "QXV0aG9ySW5mb0ZhY3RAMDoyNTk4MDcwNzQ6Wzc0MzgsIDQ5MzM5NDA2XQ==", "__typename": "AuthorInfoFact", "viewCount": 49339406, "answerCount": 7438}], "sourceNetwork": null, "sourceQuestion": null, "sourceAnswer": null, "tribeItem": null, "businessCredential": null, "businessAnswer": null, "viewerHasUpvoted": false, "numSocialVoters": 0, "numUpvotes": 441, "socialVoterNames": [], "socialVoterPhotos": [], "isDeleted": false, "viewerCanRestoreAnswer": false, "showAskerSatisfactionSurvey": false, "suggestedEdit": null, "content": "{\"sections\": [{\"spans\": [{\"text\": \"Sure. Just adopt a national biometric ID database, based on lessons learned by India with its Aadhaar system. It would have to be free and administered federally, nationwide, and then all states could adopt it as a nothing-else-needed voter ID.\", \"modifiers\": {}}], \"indent\": 0, \"quoted\": false, \"type\": \"plain\", \"is_rtl\": false}, {\"spans\": [{\"text\": \"\", \"modifiers\": {\"image\": \"https://qph.fs.quoracdn.net/main-qimg-cca107c9bd6eb73141ea8b00a4502a3a\", \"height\": 270, \"width\": 720, \"master_url\": \"https://qph.fs.quoracdn.net/main-qimg-ae8c69ecf0f1d53b85814c610963b973\", \"zoomable\": true}}], \"indent\": 0, \"quoted\": false, \"type\": \"image\", \"is_rtl\": false}, {\"spans\": [{\"text\": \"Of course all right wingers would oppose this in a hot fury. One, because as representing the Confederacy 2.0, they\\u2019re totally paranoid about the federal government. Two, they know there\\u2019s no significant voter fraud, and this would remove the fig leaf covering the depth of their racism and bias against all things liberal.\", \"modifiers\": {}}], \"indent\": 0, \"quoted\": false, \"type\": \"plain\", \"is_rtl\": false}]}", "isSensitive": false, "monetizationAccessOption": null, "numViews": 9383, "isNotForReproduction": false, "moderationCollapseType": null, "hasDisclaimer": false, "disclaimer": null, "numRequesters": 0, "requesters": [], "isCommentsDisabled": false, "isCollapsedForViewer": false, "isModerationLocked": false, "moderationCollapseTypeUrl": null, "network": {"id": "TmV0d29yazow", "__typename": "Network", "contentLanguageCode": "en"}, "collapseOperation": null, "originalQuestionIfDifferent": null, "viewerShouldPromptTopicBio": false}, "viewer": {"id": "Vmlld2VyQDA6MA==", "__typename": "Viewer", "user": null}, "notifInjectedBundleFromSncid": null}, "broadcastId": "main-w-chan52-8888-react_ebefukpcsfoypfri-8JK0", "tchannelData": {"minSeq": "0", "channel": "main-w-chan52-8888-react_ebefukpcsfoypfri-8JK0", "channelHash": "14047146917207866956", "boxName": "chan52-8888", "baseHost": "quora.com", "targetUrl": "", "enableWebsocket": true}, "broadcastData": {"categoryToDepkeys": {"Viewer:isUniversalLoggedIn:Vmlld2VyQDA6MA==": ["LIUS:3de3d53e1181e9eb06d8e65157e8d575", "LIUB:79039754b9a95a4f537373a3022eb580"]}, "depkeyToVersion": {"LIUB:79039754b9a95a4f537373a3022eb580": 0, "LIUS:3de3d53e1181e9eb06d8e65157e8d575": 0}}}